splitdataloader/__init__.py
splitdataloader/data_writer_and_loader.py
splitdataloader/multiproc_queue_itr.py
splitdataloader-0.0.1.dist-info/LICENSE
splitdataloader-0.0.1.dist-info/METADATA
splitdataloader-0.0.1.dist-info/WHEEL
splitdataloader-0.0.1.dist-info/top_level.txt
splitdataloader-0.0.1.dist-info/RECORD
