Metadata-Version: 2.1
Name: splitdataloader
Version: 0.0.1
Summary: A simple library to load training data from hdd or ssd
Author-email: Vinay Krishnan <nk.vinay@zohomail.in>
License: MIT License
Project-URL: Homepage, https://github.com/charstorm/split-data-loader/
Keywords: deep-learning,datasets
Classifier: Programming Language :: Python
Requires-Python: >=3.8
License-File: LICENSE
Provides-Extra: dev
Requires-Dist: ruff ; extra == 'dev'
Requires-Dist: pyright ; extra == 'dev'
